igeInAppPurchase.cp37-win32.pyd
igeInAppPurchase-0.0.2.dist-info/LICENSE
igeInAppPurchase-0.0.2.dist-info/METADATA
igeInAppPurchase-0.0.2.dist-info/WHEEL
igeInAppPurchase-0.0.2.dist-info/top_level.txt
igeInAppPurchase-0.0.2.dist-info/RECORD
